{
  "W07000049": {
    "consituency": "Aberavon",
    "nomination_2015": "Yvette Cooper",
    "nomination_2016": ""
  },
  "W07000058": {
    "consituency": "Aberconwy",
    "nomination_2015": "",
    "nomination_2016": ""
  },
  "S16000074": {
    "consituency": "Aberdeen Central",
    "nomination_2015": "Jeremy Corbyn",
    "nomination_2016": ""
  },
  "S16000075": {
    "consituency": "Aberdeen Donside",
    "nomination_2015": "",
    "nomination_2016": ""
  },
  "S16000076": {
    "consituency": "Aberdeen South and North Kincardine",
    "nomination_2015": "",
    "nomination_2016": ""
  },
  "S16000077": {
    "consituency": "Aberdeenshire East",
    "nomination_2015": "",
    "nomination_2016": ""
  },
  "S16000078": {
    "consituency": "Aberdeenshire West",
    "nomination_2015": "Yvette Cooper",
    "nomination_2016": "Owen Smith"
  },
  "S16000079": {
    "consituency": "Airdrie and Shotts",
    "nomination_2015": "Jeremy Corbyn",
    "nomination_2016": ""
  },
  "E14000530": {
    "consituency": "Aldershot",
    "nomination_2015": "Andy Burnham",
    "nomination_2016": ""
  },
  "E14000531": {
    "consituency": "Aldridge-Brownhills",
    "nomination_2015": "Jeremy Corbyn",
    "nomination_2016": ""
  },
  "S16000080": {
    "consituency": "Almond Valley",
    "nomination_2015": "Jeremy Corbyn",
    "nomination_2016": ""
  },
  "E14000532": {
    "consituency": "Altrincham and Sale West",
    "nomination_2015": "Yvette Cooper",
    "nomination_2016": "Owen Smith"
  },
  "W07000043": {
    "consituency": "Alyn and Deeside",
    "nomination_2015": "Jeremy Corbyn",
    "nomination_2016": ""
  },
  "E14000533": {
    "consituency": "Amber Valley",
    "nomination_2015": "Jeremy Corbyn",
    "nomination_2016": ""
  },
  "S16000081": {
    "consituency": "Angus North and Mearns",
    "nomination_2015": "",
    "nomination_2016": ""
  },
  "S16000082": {
    "consituency": "Angus South",
    "nomination_2015": "Yvette Cooper",
    "nomination_2016": ""
  },
  "W07000057": {
    "consituency": "Arfon",
    "nomination_2015": "",
    "nomination_2016": ""
  },
  "S16000083": {
    "consituency": "Argyll and Bute",
    "nomination_2015": "Yvette Cooper",
    "nomination_2016": "Jeremy Corbyn"
  },
  "E14000534": {
    "consituency": "Arundel and South Downs",
    "nomination_2015": "",
    "nomination_2016": "Jeremy Corbyn"
  },
  "E14000535": {
    "consituency": "Ashfield",
    "nomination_2015": "Jeremy Corbyn",
    "nomination_2016": ""
  },
  "E14000536": {
    "consituency": "Ashford",
    "nomination_2015": "",
    "nomination_2016": ""
  },
  "E14000537": {
    "consituency": "Ashton-under-Lyne",
    "nomination_2015": "Jeremy Corbyn",
    "nomination_2016": "Jeremy Corbyn"
  },
  "E14000538": {
    "consituency": "Aylesbury",
    "nomination_2015": "Jeremy Corbyn",
    "nomination_2016": ""
  },
  "S16000084": {
    "consituency": "Ayr",
    "nomination_2015": "Andy Burnham",
    "nomination_2016": ""
  },
  "E14000539": {
    "consituency": "Banbury",
    "nomination_2015": "",
    "nomination_2016": ""
  },
  "S16000085": {
    "consituency": "Banffshire and Buchan Coast",
    "nomination_2015": "Andy Burnham",
    "nomination_2016": ""
  },
  "E14000540": {
    "consituency": "Barking",
    "nomination_2015": "Liz Kendall",
    "nomination_2016": ""
  },
  "E14000541": {
    "consituency": "Barnsley Central",
    "nomination_2015": "",
    "nomination_2016": ""
  },
  "E14000542": {
    "consituency": "Barnsley East",
    "nomination_2015": "Andy Burnham",
    "nomination_2016": ""
  },
  "E14000543": {
    "consituency": "Barrow and Furness",
    "nomination_2015": "Andy Burnham",
    "nomination_2016": ""
  },
  "E14000544": {
    "consituency": "Basildon and Billericay",
    "nomination_2015": "Andy Burnham",
    "nomination_2016": ""
  },
  "E14000545": {
    "consituency": "Basingstoke",
    "nomination_2015": "Yvette Cooper",
    "nomination_2016": ""
  },
  "E14000546": {
    "consituency": "Bassetlaw",
    "nomination_2015": "Yvette Cooper",
    "nomination_2016": ""
  },
  "E14000547": {
    "consituency": "Bath",
    "nomination_2015": "Jeremy Corbyn",
    "nomination_2016": "Jeremy Corbyn"
  },
  "E14000548": {
    "consituency": "Batley and Spen",
    "nomination_2015": "Jeremy Corbyn",
    "nomination_2016": ""
  },
  "E14000549": {
    "consituency": "Battersea",
    "nomination_2015": "Yvette Cooper",
    "nomination_2016": "Owen Smith"
  },
  "E14000550": {
    "consituency": "Beaconsfield",
    "nomination_2015": "",
    "nomination_2016": ""
  },
  "E14000551": {
    "consituency": "Beckenham",
    "nomination_2015": "Andy Burnham",
    "nomination_2016": ""
  },
  "E14000552": {
    "consituency": "Bedford",
    "nomination_2015": "Jeremy Corbyn",
    "nomination_2016": ""
  },
  "E14000553": {
    "consituency": "Bermondsey and Old Southwark",
    "nomination_2015": "Liz Kendall",
    "nomination_2016": "Owen Smith"
  },
  "E14000554": {
    "consituency": "Berwick-upon-Tweed",
    "nomination_2015": "Jeremy Corbyn",
    "nomination_2016": "Jeremy Corbyn"
  },
  "E14000555": {
    "consituency": "Bethnal Green and Bow",
    "nomination_2015": "Jeremy Corbyn",
    "nomination_2016": "Owen Smith"
  },
  "E14000556": {
    "consituency": "Beverley and Holderness",
    "nomination_2015": "",
    "nomination_2016": "Jeremy Corbyn"
  },
  "E14000557": {
    "consituency": "Bexhill and Battle",
    "nomination_2015": "",
    "nomination_2016": ""
  },
  "E14000558": {
    "consituency": "Bexleyheath and Crayford",
    "nomination_2015": "Andy Burnham",
    "nomination_2016": ""
  },
  "E14000559": {
    "consituency": "Birkenhead",
    "nomination_2015": "",
    "nomination_2016": ""
  },
  "E14000560": {
    "consituency": "Birmingham Edgbaston",
    "nomination_2015": "",
    "nomination_2016": ""
  },
  "E14000561": {
    "consituency": "Birmingham Erdington",
    "nomination_2015": "",
    "nomination_2016": ""
  },
  "E14000562": {
    "consituency": "Birmingham Hall Green",
    "nomination_2015": "",
    "nomination_2016": "Jeremy Corbyn"
  },
  "E14000563": {
    "consituency": "Birmingham Hodge Hill",
    "nomination_2015": "Yvette Cooper",
    "nomination_2016": ""
  },
  "E14000564": {
    "consituency": "Birmingham Ladywood",
    "nomination_2015": "",
    "nomination_2016": ""
  },
  "E14000565": {
    "consituency": "Birmingham Northfield",
    "nomination_2015": "",
    "nomination_2016": ""
  },
  "E14000566": {
    "consituency": "Birmingham Perry Barr",
    "nomination_2015": "Yvette Cooper",
    "nomination_2016": ""
  },
  "E14000567": {
    "consituency": "Birmingham Selly Oak",
    "nomination_2015": "",
    "nomination_2016": ""
  },
  "E14000568": {
    "consituency": "Birmingham Yardley",
    "nomination_2015": "Jeremy Corbyn",
    "nomination_2016": ""
  },
  "E14000569": {
    "consituency": "Bishop Auckland",
    "nomination_2015": "Andy Burnham",
    "nomination_2016": ""
  },
  "E14000570": {
    "consituency": "Blackburn",
    "nomination_2015": "",
    "nomination_2016": ""
  },
  "E14000571": {
    "consituency": "Blackley and Broughton",
    "nomination_2015": "Andy Burnham",
    "nomination_2016": ""
  },
  "E14000572": {
    "consituency": "Blackpool North and Cleveleys",
    "nomination_2015": "",
    "nomination_2016": ""
  },
  "E14000573": {
    "consituency": "Blackpool South",
    "nomination_2015": "",
    "nomination_2016": ""
  },
  "W07000072": {
    "consituency": "Blaenau Gwent",
    "nomination_2015": "Jeremy Corbyn",
    "nomination_2016": "Owen Smith"
  },
  "E14000574": {
    "consituency": "Blaydon",
    "nomination_2015": "Andy Burnham",
    "nomination_2016": ""
  },
  "E14000575": {
    "consituency": "Blyth Valley",
    "nomination_2015": "Andy Burnham",
    "nomination_2016": ""
  },
  "E14000576": {
    "consituency": "Bognor Regis and Littlehampton",
    "nomination_2015": "Yvette Cooper",
    "nomination_2016": ""
  },
  "E14000577": {
    "consituency": "Bolsover",
    "nomination_2015": "",
    "nomination_2016": "Jeremy Corbyn"
  },
  "E14000578": {
    "consituency": "Bolton North East",
    "nomination_2015": "Yvette Cooper",
    "nomination_2016": ""
  },
  "E14000579": {
    "consituency": "Bolton South East",
    "nomination_2015": "Andy Burnham",
    "nomination_2016": ""
  },
  "E14000580": {
    "consituency": "Bolton West",
    "nomination_2015": "Andy Burnham",
    "nomination_2016": ""
  },
  "E14000581": {
    "consituency": "Bootle",
    "nomination_2015": "Andy Burnham",
    "nomination_2016": "Jeremy Corbyn"
  },
  "E14000582": {
    "consituency": "Boston and Skegness",
    "nomination_2015": "",
    "nomination_2016": ""
  },
  "E14000583": {
    "consituency": "Bosworth",
    "nomination_2015": "",
    "nomination_2016": ""
  },
  "E14000584": {
    "consituency": "Bournemouth East",
    "nomination_2015": "",
    "nomination_2016": "Jeremy Corbyn"
  },
  "E14000585": {
    "consituency": "Bournemouth West",
    "nomination_2015": "Jeremy Corbyn",
    "nomination_2016": "Jeremy Corbyn"
  },
  "E14000586": {
    "consituency": "Bracknell",
    "nomination_2015": "Yvette Cooper",
    "nomination_2016": ""
  },
  "E14000587": {
    "consituency": "Bradford East",
    "nomination_2015": "",
    "nomination_2016": ""
  },
  "E14000588": {
    "consituency": "Bradford South",
    "nomination_2015": "",
    "nomination_2016": ""
  },
  "E14000589": {
    "consituency": "Bradford West",
    "nomination_2015": "",
    "nomination_2016": ""
  },
  "E14000590": {
    "consituency": "Braintree",
    "nomination_2015": "",
    "nomination_2016": ""
  },
  "W07000068": {
    "consituency": "Brecon and Radnorshire",
    "nomination_2015": "Yvette Cooper",
    "nomination_2016": ""
  },
  "E14000591": {
    "consituency": "Brent Central",
    "nomination_2015": "Jeremy Corbyn",
    "nomination_2016": "Jeremy Corbyn"
  },
  "E14000592": {
    "consituency": "Brent North",
    "nomination_2015": "Jeremy Corbyn",
    "nomination_2016": ""
  },
  "E14000593": {
    "consituency": "Brentford and Isleworth",
    "nomination_2015": "",
    "nomination_2016": ""
  },
  "E14000594": {
    "consituency": "Brentwood and Ongar",
    "nomination_2015": "Andy Burnham",
    "nomination_2016": ""
  },
  "W07000073": {
    "consituency": "Bridgend",
    "nomination_2015": "Yvette Cooper",
    "nomination_2016": ""
  },
  "E14000595": {
    "consituency": "Bridgwater and West Somerset",
    "nomination_2015": "Jeremy Corbyn",
    "nomination_2016": ""
  },
  "E14000596": {
    "consituency": "Brigg and Goole",
    "nomination_2015": "Jeremy Corbyn",
    "nomination_2016": ""
  },
  "E14000597": {
    "consituency": "Brighton Kemptown",
    "nomination_2015": "",
    "nomination_2016": ""
  },
  "E14000598": {
    "consituency": "Brighton Pavilion",
    "nomination_2015": "",
    "nomination_2016": ""
  },
  "E14000599": {
    "consituency": "Bristol East",
    "nomination_2015": "Andy Burnham",
    "nomination_2016": "Jeremy Corbyn"
  },
  "E14000600": {
    "consituency": "Bristol North West",
    "nomination_2015": "Andy Burnham",
    "nomination_2016": "Jeremy Corbyn"
  },
  "E14000601": {
    "consituency": "Bristol South",
    "nomination_2015": "",
    "nomination_2016": ""
  },
  "E14000602": {
    "consituency": "Bristol West",
    "nomination_2015": "",
    "nomination_2016": ""
  },
  "E14000603": {
    "consituency": "Broadland",
    "nomination_2015": "",
    "nomination_2016": ""
  },
  "E14000604": {
    "consituency": "Bromley and Chislehurst",
    "nomination_2015": "Jeremy Corbyn",
    "nomination_2016": "Jeremy Corbyn"
  },
  "E14000605": {
    "consituency": "Bromsgrove",
    "nomination_2015": "Yvette Cooper",
    "nomination_2016": ""
  },
  "E14000606": {
    "consituency": "Broxbourne",
    "nomination_2015": "Yvette Cooper",
    "nomination_2016": ""
  },
  "E14000607": {
    "consituency": "Broxtowe",
    "nomination_2015": "Jeremy Corbyn",
    "nomination_2016": "Jeremy Corbyn"
  },
  "E14000608": {
    "consituency": "Buckingham",
    "nomination_2015": "",
    "nomination_2016": ""
  },
  "E14000609": {
    "consituency": "Burnley",
    "nomination_2015": "",
    "nomination_2016": ""
  },
  "E14000610": {
    "consituency": "Burton",
    "nomination_2015": "Andy Burnham",
    "nomination_2016": ""
  },
  "E14000611": {
    "consituency": "Bury North",
    "nomination_2015": "Yvette Cooper",
    "nomination_2016": "Jeremy Corbyn"
  },
  "E14000612": {
    "consituency": "Bury South",
    "nomination_2015": "Yvette Cooper",
    "nomination_2016": ""
  },
  "E14000613": {
    "consituency": "Bury St Edmunds",
    "nomination_2015": "Jeremy Corbyn",
    "nomination_2016": "Jeremy Corbyn"
  },
  "W07000076": {
    "consituency": "Caerphilly",
    "nomination_2015": "Yvette Cooper",
    "nomination_2016": ""
  },
  "S16000086": {
    "consituency": "Caithness Sutherland and Ross",
    "nomination_2015": "",
    "nomination_2016": ""
  },
  "E14000614": {
    "consituency": "Calder Valley",
    "nomination_2015": "Jeremy Corbyn",
    "nomination_2016": ""
  },
  "E14000615": {
    "consituency": "Camberwell and Peckham",
    "nomination_2015": "Liz Kendall",
    "nomination_2016": "Jeremy Corbyn"
  },
  "E14000616": {
    "consituency": "Camborne and Redruth",
    "nomination_2015": "",
    "nomination_2016": ""
  },
  "E14000617": {
    "consituency": "Cambridge",
    "nomination_2015": "",
    "nomination_2016": ""
  },
  "E14000618": {
    "consituency": "Cannock Chase",
    "nomination_2015": "",
    "nomination_2016": ""
  },
  "E14000619": {
    "consituency": "Canterbury",
    "nomination_2015": "",
    "nomination_2016": "Jeremy Corbyn"
  },
  "W07000050": {
    "consituency": "Cardiff Central",
    "nomination_2015": "",
    "nomination_2016": ""
  },
  "W07000051": {
    "consituency": "Cardiff North",
    "nomination_2015": "",
    "nomination_2016": ""
  },
  "W07000080": {
    "consituency": "Cardiff South and Penarth",
    "nomination_2015": "",
    "nomination_2016": ""
  },
  "W07000079": {
    "consituency": "Cardiff West",
    "nomination_2015": "",
    "nomination_2016": ""
  },
  "E14000620": {
    "consituency": "Carlisle",
    "nomination_2015": "",
    "nomination_2016": ""
  },
  "W07000067": {
    "consituency": "Carmarthen East and Dinefwr",
    "nomination_2015": "Liz Kendall",
    "nomination_2016": ""
  },
  "W07000066": {
    "consituency": "Carmarthen West and South Pembrokeshire",
    "nomination_2015": "Andy Burnham",
    "nomination_2016": ""
  },
  "S16000087": {
    "consituency": "Carrick, Cumnock and Doon Valley",
    "nomination_2015": "Andy Burnham",
    "nomination_2016": ""
  },
  "E14000621": {
    "consituency": "Carshalton and Wallington",
    "nomination_2015": "Yvette Cooper",
    "nomination_2016": ""
  },
  "E14000622": {
    "consituency": "Castle Point",
    "nomination_2015": "Jeremy Corbyn",
    "nomination_2016": ""
  },
  "E14000623": {
    "consituency": "Central Devon",
    "nomination_2015": "Jeremy Corbyn",
    "nomination_2016": ""
  },
  "E14000624": {
    "consituency": "Central Suffolk and North Ipswich",
    "nomination_2015": "",
    "nomination_2016": ""
  },
  "W07000064": {
    "consituency": "Ceredigion",
    "nomination_2015": "",
    "nomination_2016": ""
  },
  "E14000625": {
    "consituency": "Charnwood",
    "nomination_2015": "",
    "nomination_2016": "Owen Smith"
  },
  "E14000626": {
    "consituency": "Chatham and Aylesford",
    "nomination_2015": "Andy Burnham",
    "nomination_2016": ""
  },
  "E14000627": {
    "consituency": "Cheadle",
    "nomination_2015": "Andy Burnham",
    "nomination_2016": ""
  },
  "E14000628": {
    "consituency": "Chelmsford",
    "nomination_2015": "Yvette Cooper",
    "nomination_2016": ""
  },
  "E14000629": {
    "consituency": "Chelsea and Fulham",
    "nomination_2015": "Yvette Cooper",
    "nomination_2016": ""
  },
  "E14000630": {
    "consituency": "Cheltenham",
    "nomination_2015": "",
    "nomination_2016": "Jeremy Corbyn"
  },
  "E14000631": {
    "consituency": "Chesham and Amersham",
    "nomination_2015": "Yvette Cooper",
    "nomination_2016": "Jeremy Corbyn"
  },
  "E14000632": {
    "consituency": "Chesterfield",
    "nomination_2015": "",
    "nomination_2016": "Jeremy Corbyn"
  },
  "E14000633": {
    "consituency": "Chichester",
    "nomination_2015": "",
    "nomination_2016": ""
  },
  "E14000634": {
    "consituency": "Chingford and Woodford Green",
    "nomination_2015": "Jeremy Corbyn",
    "nomination_2016": "Jeremy Corbyn"
  },
  "E14000635": {
    "consituency": "Chippenham",
    "nomination_2015": "Yvette Cooper",
    "nomination_2016": "Jeremy Corbyn"
  },
  "E14000636": {
    "consituency": "Chipping Barnet",
    "nomination_2015": "Yvette Cooper",
    "nomination_2016": ""
  },
  "E14000637": {
    "consituency": "Chorley",
    "nomination_2015": "",
    "nomination_2016": ""
  },
  "E14000638": {
    "consituency": "Christchurch",
    "nomination_2015": "Yvette Cooper",
    "nomination_2016": ""
  },
  "E14000639": {
    "consituency": "Cities of London and Westminster",
    "nomination_2015": "Liz Kendall",
    "nomination_2016": ""
  },
  "E14000640": {
    "consituency": "City of Chester",
    "nomination_2015": "",
    "nomination_2016": ""
  },
  "E14000641": {
    "consituency": "City of Durham",
    "nomination_2015": "",
    "nomination_2016": ""
  },
  "S16000088": {
    "consituency": "Clackmannanshire and Dunblane",
    "nomination_2015": "Andy Burnham",
    "nomination_2016": ""
  },
  "E14000642": {
    "consituency": "Clacton",
    "nomination_2015": "",
    "nomination_2016": ""
  },
  "E14000643": {
    "consituency": "Cleethorpes",
    "nomination_2015": "",
    "nomination_2016": ""
  },
  "W07000062": {
    "consituency": "Clwyd South",
    "nomination_2015": "",
    "nomination_2016": ""
  },
  "W07000059": {
    "consituency": "Clwyd West",
    "nomination_2015": "",
    "nomination_2016": "Jeremy Corbyn"
  },
  "S16000089": {
    "consituency": "Clydebank and Milngavie",
    "nomination_2015": "Yvette Cooper",
    "nomination_2016": ""
  },
  "S16000090": {
    "consituency": "Clydesdale",
    "nomination_2015": "",
    "nomination_2016": ""
  },
  "S16000091": {
    "consituency": "Coatbridge and Chryston",
    "nomination_2015": "",
    "nomination_2016": ""
  },
  "E14000644": {
    "consituency": "Colchester",
    "nomination_2015": "Yvette Cooper",
    "nomination_2016": "Jeremy Corbyn"
  },
  "E14000645": {
    "consituency": "Colne Valley",
    "nomination_2015": "",
    "nomination_2016": ""
  },
  "E14000646": {
    "consituency": "Congleton",
    "nomination_2015": "Andy Burnham",
    "nomination_2016": "Jeremy Corbyn"
  },
  "E14000647": {
    "consituency": "Copeland",
    "nomination_2015": "Andy Burnham",
    "nomination_2016": ""
  },
  "E14000648": {
    "consituency": "Corby",
    "nomination_2015": "",
    "nomination_2016": ""
  },
  "E14000649": {
    "consituency": "Coventry North East",
    "nomination_2015": "",
    "nomination_2016": ""
  },
  "E14000650": {
    "consituency": "Coventry North West",
    "nomination_2015": "",
    "nomination_2016": ""
  },
  "E14000651": {
    "consituency": "Coventry South",
    "nomination_2015": "Yvette Cooper",
    "nomination_2016": ""
  },
  "S16000092": {
    "consituency": "Cowdenbeath",
    "nomination_2015": "",
    "nomination_2016": ""
  },
  "E14000652": {
    "consituency": "Crawley",
    "nomination_2015": "Yvette Cooper",
    "nomination_2016": ""
  },
  "E14000653": {
    "consituency": "Crewe and Nantwich",
    "nomination_2015": "Jeremy Corbyn",
    "nomination_2016": "Jeremy Corbyn"
  },
  "E14000654": {
    "consituency": "Croydon Central",
    "nomination_2015": "Jeremy Corbyn",
    "nomination_2016": "Jeremy Corbyn"
  },
  "E14000655": {
    "consituency": "Croydon North",
    "nomination_2015": "Jeremy Corbyn",
    "nomination_2016": "Jeremy Corbyn"
  },
  "E14000656": {
    "consituency": "Croydon South",
    "nomination_2015": "Liz Kendall",
    "nomination_2016": ""
  },
  "S16000093": {
    "consituency": "Cumbernauld and Kilsyth",
    "nomination_2015": "Andy Burnham",
    "nomination_2016": ""
  },
  "S16000094": {
    "consituency": "Cunninghame North",
    "nomination_2015": "",
    "nomination_2016": ""
  },
  "S16000095": {
    "consituency": "Cunninghame South",
    "nomination_2015": "Yvette Cooper",
    "nomination_2016": "Jeremy Corbyn"
  },
  "W07000070": {
    "consituency": "Cynon Valley",
    "nomination_2015": "",
    "nomination_2016": ""
  },
  "E14000657": {
    "consituency": "Dagenham and Rainham",
    "nomination_2015": "Jeremy Corbyn",
    "nomination_2016": "Jeremy Corbyn"
  },
  "E14000658": {
    "consituency": "Darlington",
    "nomination_2015": "",
    "nomination_2016": ""
  },
  "E14000659": {
    "consituency": "Dartford",
    "nomination_2015": "Andy Burnham",
    "nomination_2016": ""
  },
  "E14000660": {
    "consituency": "Daventry",
    "nomination_2015": "",
    "nomination_2016": ""
  },
  "W07000042": {
    "consituency": "Delyn",
    "nomination_2015": "Yvette Cooper",
    "nomination_2016": "Jeremy Corbyn"
  },
  "E14000661": {
    "consituency": "Denton and Reddish",
    "nomination_2015": "",
    "nomination_2016": ""
  },
  "E14000662": {
    "consituency": "Derby North",
    "nomination_2015": "Jeremy Corbyn",
    "nomination_2016": ""
  },
  "E14000663": {
    "consituency": "Derby South",
    "nomination_2015": "Andy Burnham",
    "nomination_2016": ""
  },
  "E14000664": {
    "consituency": "Derbyshire Dales",
    "nomination_2015": "Jeremy Corbyn",
    "nomination_2016": ""
  },
  "E14000665": {
    "consituency": "Devizes",
    "nomination_2015": "Jeremy Corbyn",
    "nomination_2016": "Jeremy Corbyn"
  },
  "E14000666": {
    "consituency": "Dewsbury",
    "nomination_2015": "",
    "nomination_2016": ""
  },
  "E14000667": {
    "consituency": "Don Valley",
    "nomination_2015": "Andy Burnham",
    "nomination_2016": ""
  },
  "E14000668": {
    "consituency": "Doncaster Central",
    "nomination_2015": "Jeremy Corbyn",
    "nomination_2016": ""
  },
  "E14000669": {
    "consituency": "Doncaster North",
    "nomination_2015": "",
    "nomination_2016": ""
  },
  "E14000670": {
    "consituency": "Dover",
    "nomination_2015": "",
    "nomination_2016": ""
  },
  "E14000671": {
    "consituency": "Dudley North",
    "nomination_2015": "Andy Burnham",
    "nomination_2016": ""
  },
  "E14000672": {
    "consituency": "Dudley South",
    "nomination_2015": "Andy Burnham",
    "nomination_2016": ""
  },
  "E14000673": {
    "consituency": "Dulwich and West Norwood",
    "nomination_2015": "Liz Kendall",
    "nomination_2016": ""
  },
  "S16000096": {
    "consituency": "Dumbarton",
    "nomination_2015": "",
    "nomination_2016": ""
  },
  "S16000097": {
    "consituency": "Dumfriesshire",
    "nomination_2015": "",
    "nomination_2016": ""
  },
  "S16000098": {
    "consituency": "Dundee City East",
    "nomination_2015": "Jeremy Corbyn",
    "nomination_2016": ""
  },
  "S16000099": {
    "consituency": "Dundee City West",
    "nomination_2015": "Jeremy Corbyn",
    "nomination_2016": ""
  },
  "S16000100": {
    "consituency": "Dunfermline",
    "nomination_2015": "Andy Burnham",
    "nomination_2016": ""
  },
  "W07000061": {
    "consituency": "Dwyfor Meirionnydd",
    "nomination_2015": "",
    "nomination_2016": "Jeremy Corbyn"
  },
  "E14000674": {
    "consituency": "Ealing Central and Acton",
    "nomination_2015": "Yvette Cooper",
    "nomination_2016": ""
  },
  "E14000675": {
    "consituency": "Ealing North",
    "nomination_2015": "",
    "nomination_2016": ""
  },
  "E14000676": {
    "consituency": "Ealing Southall",
    "nomination_2015": "Andy Burnham",
    "nomination_2016": ""
  },
  "E14000677": {
    "consituency": "Easington",
    "nomination_2015": "Jeremy Corbyn",
    "nomination_2016": "Jeremy Corbyn"
  },
  "E14000678": {
    "consituency": "East Devon",
    "nomination_2015": "Jeremy Corbyn",
    "nomination_2016": "Jeremy Corbyn"
  },
  "E14000679": {
    "consituency": "East Ham",
    "nomination_2015": "Liz Kendall",
    "nomination_2016": ""
  },
  "E14000680": {
    "consituency": "East Hampshire",
    "nomination_2015": "",
    "nomination_2016": ""
  },
  "S16000101": {
    "consituency": "East Kilbride",
    "nomination_2015": "Andy Burnham",
    "nomination_2016": ""
  },
  "S16000102": {
    "consituency": "East Lothian",
    "nomination_2015": "",
    "nomination_2016": "Owen Smith"
  },
  "E14000681": {
    "consituency": "East Surrey",
    "nomination_2015": "Andy Burnham",
    "nomination_2016": "Jeremy Corbyn"
  },
  "E14000682": {
    "consituency": "East Worthing and Shoreham",
    "nomination_2015": "",
    "nomination_2016": "Jeremy Corbyn"
  },
  "E14000683": {
    "consituency": "East Yorkshire",
    "nomination_2015": "",
    "nomination_2016": ""
  },
  "E14000684": {
    "consituency": "Eastbourne",
    "nomination_2015": "Andy Burnham",
    "nomination_2016": ""
  },
  "E14000685": {
    "consituency": "Eastleigh",
    "nomination_2015": "",
    "nomination_2016": "Jeremy Corbyn"
  },
  "S16000103": {
    "consituency": "Eastwood",
    "nomination_2015": "Andy Burnham",
    "nomination_2016": ""
  },
  "E14000686": {
    "consituency": "Eddisbury",
    "nomination_2015": "",
    "nomination_2016": ""
  },
  "S16000104": {
    "consituency": "Edinburgh Central",
    "nomination_2015": "Jeremy Corbyn",
    "nomination_2016": ""
  },
  "S16000105": {
    "consituency": "Edinburgh Eastern",
    "nomination_2015": "Yvette Cooper",
    "nomination_2016": ""
  },
  "S16000106": {
    "consituency": "Edinburgh Northern and Leith",
    "nomination_2015": "Jeremy Corbyn",
    "nomination_2016": "Jeremy Corbyn"
  },
  "S16000107": {
    "consituency": "Edinburgh Pentlands",
    "nomination_2015": "Jeremy Corbyn",
    "nomination_2016": ""
  },
  "S16000108": {
    "consituency": "Edinburgh Southern",
    "nomination_2015": "",
    "nomination_2016": ""
  },
  "S16000109": {
    "consituency": "Edinburgh Western",
    "nomination_2015": "Jeremy Corbyn",
    "nomination_2016": ""
  },
  "E14000687": {
    "consituency": "Edmonton",
    "nomination_2015": "Jeremy Corbyn",
    "nomination_2016": ""
  },
  "E14000688": {
    "consituency": "Ellesmere Port and Neston",
    "nomination_2015": "Jeremy Corbyn",
    "nomination_2016": ""
  },
  "E14000689": {
    "consituency": "Elmet and Rothwell",
    "nomination_2015": "Jeremy Corbyn",
    "nomination_2016": ""
  },
  "E14000690": {
    "consituency": "Eltham",
    "nomination_2015": "",
    "nomination_2016": ""
  },
  "E14000691": {
    "consituency": "Enfield North",
    "nomination_2015": "Jeremy Corbyn",
    "nomination_2016": ""
  },
  "E14000692": {
    "consituency": "Enfield Southgate",
    "nomination_2015": "Jeremy Corbyn",
    "nomination_2016": "Jeremy Corbyn"
  },
  "E14000693": {
    "consituency": "Epping Forest",
    "nomination_2015": "",
    "nomination_2016": ""
  },
  "E14000694": {
    "consituency": "Epsom and Ewell",
    "nomination_2015": "Andy Burnham",
    "nomination_2016": ""
  },
  "E14000695": {
    "consituency": "Erewash",
    "nomination_2015": "Yvette Cooper",
    "nomination_2016": ""
  },
  "E14000696": {
    "consituency": "Erith and Thamesmead",
    "nomination_2015": "Jeremy Corbyn",
    "nomination_2016": "Jeremy Corbyn"
  },
  "E14000697": {
    "consituency": "Esher and Walton",
    "nomination_2015": "",
    "nomination_2016": ""
  },
  "S16000111": {
    "consituency": "Ettrick Roxburgh and Berwickshire",
    "nomination_2015": "",
    "nomination_2016": ""
  },
  "E14000698": {
    "consituency": "Exeter",
    "nomination_2015": "Yvette Cooper",
    "nomination_2016": ""
  },
  "S16000112": {
    "consituency": "Falkirk East",
    "nomination_2015": "",
    "nomination_2016": ""
  },
  "S16000113": {
    "consituency": "Falkirk West",
    "nomination_2015": "",
    "nomination_2016": ""
  },
  "E14000699": {
    "consituency": "Fareham",
    "nomination_2015": "",
    "nomination_2016": ""
  },
  "E14000700": {
    "consituency": "Faversham and Mid Kent",
    "nomination_2015": "",
    "nomination_2016": ""
  },
  "E14000701": {
    "consituency": "Feltham and Heston",
    "nomination_2015": "",
    "nomination_2016": ""
  },
  "E14000702": {
    "consituency": "Filton and Bradley Stoke",
    "nomination_2015": "",
    "nomination_2016": ""
  },
  "E14000703": {
    "consituency": "Finchley and Golders Green",
    "nomination_2015": "Andy Burnham",
    "nomination_2016": "Owen Smith"
  },
  "E14000704": {
    "consituency": "Folkestone and Hythe",
    "nomination_2015": "Andy Burnham",
    "nomination_2016": "Jeremy Corbyn"
  },
  "E14000705": {
    "consituency": "Forest of Dean",
    "nomination_2015": "Andy Burnham",
    "nomination_2016": ""
  },
  "E14000706": {
    "consituency": "Fylde",
    "nomination_2015": "",
    "nomination_2016": ""
  },
  "E14000707": {
    "consituency": "Gainsborough",
    "nomination_2015": "",
    "nomination_2016": "Jeremy Corbyn"
  },
  "S16000114": {
    "consituency": "Galloway and West Dumfries",
    "nomination_2015": "Yvette Cooper",
    "nomination_2016": ""
  },
  "E14000708": {
    "consituency": "Garston and Halewood",
    "nomination_2015": "Yvette Cooper",
    "nomination_2016": ""
  },
  "E14000709": {
    "consituency": "Gateshead",
    "nomination_2015": "Jeremy Corbyn",
    "nomination_2016": "Jeremy Corbyn"
  },
  "E14000710": {
    "consituency": "Gedling",
    "nomination_2015": "",
    "nomination_2016": ""
  },
  "E14000711": {
    "consituency": "Gillingham and Rainham",
    "nomination_2015": "",
    "nomination_2016": ""
  },
  "S16000115": {
    "consituency": "Glasgow Anniesland",
    "nomination_2015": "Yvette Cooper",
    "nomination_2016": ""
  },
  "S16000116": {
    "consituency": "Glasgow Cathcart",
    "nomination_2015": "Yvette Cooper",
    "nomination_2016": ""
  },
  "S16000117": {
    "consituency": "Glasgow Kelvin",
    "nomination_2015": "Yvette Cooper",
    "nomination_2016": "Jeremy Corbyn"
  },
  "S16000118": {
    "consituency": "Glasgow Maryhill and Springburn",
    "nomination_2015": "Jeremy Corbyn",
    "nomination_2016": ""
  },
  "S16000119": {
    "consituency": "Glasgow Pollok",
    "nomination_2015": "Jeremy Corbyn",
    "nomination_2016": ""
  },
  "S16000120": {
    "consituency": "Glasgow Provan",
    "nomination_2015": "Andy Burnham",
    "nomination_2016": ""
  },
  "S16000121": {
    "consituency": "Glasgow Shettleston",
    "nomination_2015": "Andy Burnham",
    "nomination_2016": ""
  },
  "S16000122": {
    "consituency": "Glasgow Southside",
    "nomination_2015": "Andy Burnham",
    "nomination_2016": ""
  },
  "E14000712": {
    "consituency": "Gloucester",
    "nomination_2015": "Andy Burnham",
    "nomination_2016": ""
  },
  "E14000713": {
    "consituency": "Gosport",
    "nomination_2015": "",
    "nomination_2016": ""
  },
  "W07000046": {
    "consituency": "Gower",
    "nomination_2015": "Jeremy Corbyn",
    "nomination_2016": "Jeremy Corbyn"
  },
  "E14000714": {
    "consituency": "Grantham and Stamford",
    "nomination_2015": "Jeremy Corbyn",
    "nomination_2016": "Jeremy Corbyn"
  },
  "E14000715": {
    "consituency": "Gravesham",
    "nomination_2015": "Yvette Cooper",
    "nomination_2016": ""
  },
  "E14000716": {
    "consituency": "Great Grimsby",
    "nomination_2015": "Yvette Cooper",
    "nomination_2016": "Owen Smith"
  },
  "E14000717": {
    "consituency": "Great Yarmouth",
    "nomination_2015": "Jeremy Corbyn",
    "nomination_2016": "Jeremy Corbyn"
  },
  "S16000123": {
    "consituency": "Greenock and Inverclyde",
    "nomination_2015": "Jeremy Corbyn",
    "nomination_2016": ""
  },
  "E14000718": {
    "consituency": "Greenwich and Woolwich",
    "nomination_2015": "Yvette Cooper",
    "nomination_2016": ""
  },
  "E14000719": {
    "consituency": "Guildford",
    "nomination_2015": "",
    "nomination_2016": ""
  },
  "E14000720": {
    "consituency": "Hackney North and Stoke Newington",
    "nomination_2015": "Jeremy Corbyn",
    "nomination_2016": "Jeremy Corbyn"
  },
  "E14000721": {
    "consituency": "Hackney South and Shoreditch",
    "nomination_2015": "Yvette Cooper",
    "nomination_2016": "Jeremy Corbyn"
  },
  "E14000722": {
    "consituency": "Halesowen and Rowley Regis",
    "nomination_2015": "Andy Burnham",
    "nomination_2016": ""
  },
  "E14000723": {
    "consituency": "Halifax",
    "nomination_2015": "Jeremy Corbyn",
    "nomination_2016": ""
  },
  "E14000724": {
    "consituency": "Haltemprice and Howden",
    "nomination_2015": "",
    "nomination_2016": ""
  },
  "E14000725": {
    "consituency": "Halton",
    "nomination_2015": "Andy Burnham",
    "nomination_2016": "Jeremy Corbyn"
  },
  "S16000124": {
    "consituency": "Hamilton, Larkhall and Stonehouse",
    "nomination_2015": "Andy Burnham",
    "nomination_2016": "Jeremy Corbyn"
  },
  "E14000726": {
    "consituency": "Hammersmith",
    "nomination_2015": "Yvette Cooper",
    "nomination_2016": ""
  },
  "E14000727": {
    "consituency": "Hampstead and Kilburn",
    "nomination_2015": "Yvette Cooper",
    "nomination_2016": "Jeremy Corbyn"
  },
  "E14000728": {
    "consituency": "Harborough",
    "nomination_2015": "Jeremy Corbyn",
    "nomination_2016": ""
  },
  "E14000729": {
    "consituency": "Harlow",
    "nomination_2015": "Andy Burnham",
    "nomination_2016": "Jeremy Corbyn"
  },
  "E14000730": {
    "consituency": "Harrogate and Knaresborough",
    "nomination_2015": "Yvette Cooper",
    "nomination_2016": "Jeremy Corbyn"
  },
  "E14000731": {
    "consituency": "Harrow East",
    "nomination_2015": "Jeremy Corbyn",
    "nomination_2016": "Jeremy Corbyn"
  },
  "E14000732": {
    "consituency": "Harrow West",
    "nomination_2015": "Yvette Cooper",
    "nomination_2016": ""
  },
  "E14000733": {
    "consituency": "Hartlepool",
    "nomination_2015": "Jeremy Corbyn",
    "nomination_2016": ""
  },
  "E14000734": {
    "consituency": "Harwich and North Essex",
    "nomination_2015": "",
    "nomination_2016": "Jeremy Corbyn"
  },
  "E14000735": {
    "consituency": "Hastings and Rye",
    "nomination_2015": "",
    "nomination_2016": "Jeremy Corbyn"
  },
  "E14000736": {
    "consituency": "Havant",
    "nomination_2015": "Jeremy Corbyn",
    "nomination_2016": ""
  },
  "E14000737": {
    "consituency": "Hayes and Harlington",
    "nomination_2015": "Jeremy Corbyn",
    "nomination_2016": "Jeremy Corbyn"
  },
  "E14000738": {
    "consituency": "Hazel Grove",
    "nomination_2015": "",
    "nomination_2016": ""
  },
  "E14000739": {
    "consituency": "Hemel Hempstead",
    "nomination_2015": "Jeremy Corbyn",
    "nomination_2016": ""
  },
  "E14000740": {
    "consituency": "Hemsworth",
    "nomination_2015": "Jeremy Corbyn",
    "nomination_2016": ""
  },
  "E14000741": {
    "consituency": "Hendon",
    "nomination_2015": "Yvette Cooper",
    "nomination_2016": ""
  },
  "E14000742": {
    "consituency": "Henley",
    "nomination_2015": "",
    "nomination_2016": ""
  },
  "E14000743": {
    "consituency": "Hereford and South Herefordshire",
    "nomination_2015": "",
    "nomination_2016": "Jeremy Corbyn"
  },
  "E14000744": {
    "consituency": "Hertford and Stortford",
    "nomination_2015": "",
    "nomination_2016": ""
  },
  "E14000745": {
    "consituency": "Hertsmere",
    "nomination_2015": "Yvette Cooper",
    "nomination_2016": ""
  },
  "E14000746": {
    "consituency": "Hexham",
    "nomination_2015": "Yvette Cooper",
    "nomination_2016": ""
  },
  "E14000747": {
    "consituency": "Heywood and Middleton",
    "nomination_2015": "Andy Burnham",
    "nomination_2016": ""
  },
  "E14000748": {
    "consituency": "High Peak",
    "nomination_2015": "",
    "nomination_2016": ""
  },
  "E14000749": {
    "consituency": "Hitchin and Harpenden",
    "nomination_2015": "Yvette Cooper",
    "nomination_2016": ""
  },
  "E14000750": {
    "consituency": "Holborn and St Pancras",
    "nomination_2015": "Jeremy Corbyn",
    "nomination_2016": ""
  },
  "E14000751": {
    "consituency": "Hornchurch and Upminster",
    "nomination_2015": "Andy Burnham",
    "nomination_2016": ""
  },
  "E14000752": {
    "consituency": "Hornsey and Wood Green",
    "nomination_2015": "Jeremy Corbyn",
    "nomination_2016": ""
  },
  "E14000753": {
    "consituency": "Horsham",
    "nomination_2015": "Jeremy Corbyn",
    "nomination_2016": "Jeremy Corbyn"
  },
  "E14000754": {
    "consituency": "Houghton and Sunderland South",
    "nomination_2015": "",
    "nomination_2016": ""
  },
  "E14000755": {
    "consituency": "Hove",
    "nomination_2015": "",
    "nomination_2016": ""
  },
  "E14000756": {
    "consituency": "Huddersfield",
    "nomination_2015": "",
    "nomination_2016": ""
  },
  "E14000757": {
    "consituency": "Huntingdon",
    "nomination_2015": "",
    "nomination_2016": ""
  },
  "E14000758": {
    "consituency": "Hyndburn",
    "nomination_2015": "",
    "nomination_2016": ""
  },
  "E14000759": {
    "consituency": "Ilford North",
    "nomination_2015": "Liz Kendall",
    "nomination_2016": ""
  },
  "E14000760": {
    "consituency": "Ilford South",
    "nomination_2015": "Jeremy Corbyn",
    "nomination_2016": "Jeremy Corbyn"
  },
  "S16000125": {
    "consituency": "Inverness and Nairn",
    "nomination_2015": "Yvette Cooper",
    "nomination_2016": ""
  },
  "E14000761": {
    "consituency": "Ipswich",
    "nomination_2015": "",
    "nomination_2016": ""
  },
  "E14000762": {
    "consituency": "Isle of Wight",
    "nomination_2015": "Jeremy Corbyn",
    "nomination_2016": ""
  },
  "E14000763": {
    "consituency": "Islington North",
    "nomination_2015": "Jeremy Corbyn",
    "nomination_2016": ""
  },
  "E14000764": {
    "consituency": "Islington South and Finsbury",
    "nomination_2015": "Jeremy Corbyn",
    "nomination_2016": "Jeremy Corbyn"
  },
  "W07000077": {
    "consituency": "Islwyn",
    "nomination_2015": "",
    "nomination_2016": ""
  },
  "E14000765": {
    "consituency": "Jarrow",
    "nomination_2015": "Andy Burnham",
    "nomination_2016": "Jeremy Corbyn"
  },
  "E14000766": {
    "consituency": "Keighley",
    "nomination_2015": "",
    "nomination_2016": ""
  },
  "E14000767": {
    "consituency": "Kenilworth and Southam",
    "nomination_2015": "Yvette Cooper",
    "nomination_2016": ""
  },
  "E14000768": {
    "consituency": "Kensington",
    "nomination_2015": "Jeremy Corbyn",
    "nomination_2016": "Jeremy Corbyn"
  },
  "E14000769": {
    "consituency": "Kettering",
    "nomination_2015": "",
    "nomination_2016": ""
  },
  "S16000126": {
    "consituency": "Kilmarnock and Irvine Valley",
    "nomination_2015": "Jeremy Corbyn",
    "nomination_2016": ""
  },
  "E14000770": {
    "consituency": "Kingston and Surbiton",
    "nomination_2015": "",
    "nomination_2016": ""
  },
  "E14000771": {
    "consituency": "Kingston upon Hull East",
    "nomination_2015": "Andy Burnham",
    "nomination_2016": ""
  },
  "E14000772": {
    "consituency": "Kingston upon Hull North",
    "nomination_2015": "Jeremy Corbyn",
    "nomination_2016": ""
  },
  "E14000773": {
    "consituency": "Kingston upon Hull West and Hessl",
    "nomination_2015": "",
    "nomination_2016": ""
  },
  "E14000774": {
    "consituency": "Kingswood",
    "nomination_2015": "Andy Burnham",
    "nomination_2016": "Jeremy Corbyn"
  },
  "S16000127": {
    "consituency": "Kirkcaldy",
    "nomination_2015": "",
    "nomination_2016": "Jeremy Corbyn"
  },
  "E14000775": {
    "consituency": "Knowsley",
    "nomination_2015": "Andy Burnham",
    "nomination_2016": ""
  },
  "E14000776": {
    "consituency": "Lancaster and Fleetwood",
    "nomination_2015": "Andy Burnham",
    "nomination_2016": "Jeremy Corbyn"
  },
  "E14000777": {
    "consituency": "Leeds Central",
    "nomination_2015": "",
    "nomination_2016": ""
  },
  "E14000778": {
    "consituency": "Leeds East",
    "nomination_2015": "Jeremy Corbyn",
    "nomination_2016": "Jeremy Corbyn"
  },
  "E14000779": {
    "consituency": "Leeds North East",
    "nomination_2015": "Jeremy Corbyn",
    "nomination_2016": ""
  },
  "E14000780": {
    "consituency": "Leeds North West",
    "nomination_2015": "Jeremy Corbyn",
    "nomination_2016": "Jeremy Corbyn"
  },
  "E14000781": {
    "consituency": "Leeds West",
    "nomination_2015": "Jeremy Corbyn",
    "nomination_2016": ""
  },
  "E14000782": {
    "consituency": "Leicester East",
    "nomination_2015": "Yvette Cooper",
    "nomination_2016": "Owen Smith"
  },
  "E14000783": {
    "consituency": "Leicester South",
    "nomination_2015": "Jeremy Corbyn",
    "nomination_2016": ""
  },
  "E14000784": {
    "consituency": "Leicester West",
    "nomination_2015": "Liz Kendall",
    "nomination_2016": ""
  },
  "E14000785": {
    "consituency": "Leigh",
    "nomination_2015": "Andy Burnham",
    "nomination_2016": ""
  },
  "E14000786": {
    "consituency": "Lewes",
    "nomination_2015": "",
    "nomination_2016": "Jeremy Corbyn"
  },
  "E14000787": {
    "consituency": "Lewisham East",
    "nomination_2015": "Liz Kendall",
    "nomination_2016": ""
  },
  "E14000788": {
    "consituency": "Lewisham West and Penge",
    "nomination_2015": "Jeremy Corbyn",
    "nomination_2016": ""
  },
  "E14000789": {
    "consituency": "Lewisham Deptford",
    "nomination_2015": "Jeremy Corbyn",
    "nomination_2016": ""
  },
  "E14000790": {
    "consituency": "Leyton and Wanstead",
    "nomination_2015": "Jeremy Corbyn",
    "nomination_2016": ""
  },
  "E14000791": {
    "consituency": "Lichfield",
    "nomination_2015": "",
    "nomination_2016": ""
  },
  "E14000792": {
    "consituency": "Lincoln",
    "nomination_2015": "",
    "nomination_2016": "Jeremy Corbyn"
  },
  "S16000128": {
    "consituency": "Linlithgow",
    "nomination_2015": "Jeremy Corbyn",
    "nomination_2016": ""
  },
  "E14000793": {
    "consituency": "Liverpool Riverside",
    "nomination_2015": "Yvette Cooper",
    "nomination_2016": ""
  },
  "E14000794": {
    "consituency": "Liverpool Walton",
    "nomination_2015": "Andy Burnham",
    "nomination_2016": "Jeremy Corbyn"
  },
  "E14000795": {
    "consituency": "Liverpool Wavertree",
    "nomination_2015": "",
    "nomination_2016": ""
  },
  "E14000796": {
    "consituency": "Liverpool West Derby",
    "nomination_2015": "Andy Burnham",
    "nomination_2016": "Jeremy Corbyn"
  },
  "W07000045": {
    "consituency": "Llanelli",
    "nomination_2015": "",
    "nomination_2016": ""
  },
  "E14000797": {
    "consituency": "Loughborough",
    "nomination_2015": "Yvette Cooper",
    "nomination_2016": ""
  },
  "E14000798": {
    "consituency": "Louth and Horncastle",
    "nomination_2015": "",
    "nomination_2016": ""
  },
  "E14000799": {
    "consituency": "Ludlow",
    "nomination_2015": "",
    "nomination_2016": ""
  },
  "E14000800": {
    "consituency": "Luton North",
    "nomination_2015": "Jeremy Corbyn",
    "nomination_2016": "Jeremy Corbyn"
  },
  "E14000801": {
    "consituency": "Luton South",
    "nomination_2015": "Jeremy Corbyn",
    "nomination_2016": ""
  },
  "E14000802": {
    "consituency": "Macclesfield",
    "nomination_2015": "Yvette Cooper",
    "nomination_2016": "Jeremy Corbyn"
  },
  "E14000803": {
    "consituency": "Maidenhead",
    "nomination_2015": "Andy Burnham",
    "nomination_2016": "Jeremy Corbyn"
  },
  "E14000804": {
    "consituency": "Maidstone and The Weald",
    "nomination_2015": "",
    "nomination_2016": ""
  },
  "E14000805": {
    "consituency": "Makerfield",
    "nomination_2015": "Andy Burnham",
    "nomination_2016": ""
  },
  "E14000806": {
    "consituency": "Maldon",
    "nomination_2015": "",
    "nomination_2016": ""
  },
  "E14000807": {
    "consituency": "Manchester Central",
    "nomination_2015": "Andy Burnham",
    "nomination_2016": ""
  },
  "E14000808": {
    "consituency": "Manchester Gorton",
    "nomination_2015": "Jeremy Corbyn",
    "nomination_2016": ""
  },
  "E14000809": {
    "consituency": "Manchester Withington",
    "nomination_2015": "Yvette Cooper",
    "nomination_2016": ""
  },
  "E14000810": {
    "consituency": "Mansfield",
    "nomination_2015": "Andy Burnham",
    "nomination_2016": ""
  },
  "E14000811": {
    "consituency": "Meon Valley",
    "nomination_2015": "",
    "nomination_2016": ""
  },
  "E14000812": {
    "consituency": "Meriden",
    "nomination_2015": "",
    "nomination_2016": ""
  },
  "W07000071": {
    "consituency": "Merthyr Tydfil and Rhymney",
    "nomination_2015": "Jeremy Corbyn",
    "nomination_2016": ""
  },
  "E14000813": {
    "consituency": "Mid Bedfordshire",
    "nomination_2015": "",
    "nomination_2016": ""
  },
  "E14000814": {
    "consituency": "Mid Derbyshire",
    "nomination_2015": "",
    "nomination_2016": "Jeremy Corbyn"
  },
  "E14000815": {
    "consituency": "Mid Dorset and North Poole",
    "nomination_2015": "",
    "nomination_2016": ""
  },
  "S16000129": {
    "consituency": "Mid Fife and Glenrothes",
    "nomination_2015": "Jeremy Corbyn",
    "nomination_2016": ""
  },
  "E14000816": {
    "consituency": "Mid Norfolk",
    "nomination_2015": "",
    "nomination_2016": ""
  },
  "E14000817": {
    "consituency": "Mid Sussex",
    "nomination_2015": "Andy Burnham",
    "nomination_2016": ""
  },
  "E14000818": {
    "consituency": "Mid Worcestershire",
    "nomination_2015": "Andy Burnham",
    "nomination_2016": ""
  },
  "E14000819": {
    "consituency": "Middlesbrough",
    "nomination_2015": "Andy Burnham",
    "nomination_2016": "Jeremy Corbyn"
  },
  "E14000820": {
    "consituency": "Middlesbrough South and East Clev",
    "nomination_2015": "",
    "nomination_2016": ""
  },
  "S16000130": {
    "consituency": "Midlothian North and Musselburgh",
    "nomination_2015": "Jeremy Corbyn",
    "nomination_2016": ""
  },
  "S16000131": {
    "consituency": "Midlothian South, Tweedale and Lauderdale",
    "nomination_2015": "Andy Burnham",
    "nomination_2016": ""
  },
  "E14000821": {
    "consituency": "Milton Keynes North",
    "nomination_2015": "",
    "nomination_2016": "Jeremy Corbyn"
  },
  "E14000822": {
    "consituency": "Milton Keynes South",
    "nomination_2015": "",
    "nomination_2016": "Jeremy Corbyn"
  },
  "E14000823": {
    "consituency": "Mitcham and Morden",
    "nomination_2015": "Liz Kendall",
    "nomination_2016": ""
  },
  "E14000824": {
    "consituency": "Mole Valley",
    "nomination_2015": "",
    "nomination_2016": ""
  },
  "W07000054": {
    "consituency": "Monmouth",
    "nomination_2015": "",
    "nomination_2016": "Jeremy Corbyn"
  },
  "W07000063": {
    "consituency": "Montgomeryshire",
    "nomination_2015": "",
    "nomination_2016": ""
  },
  "S16000132": {
    "consituency": "Moray",
    "nomination_2015": "Liz Kendall",
    "nomination_2016": "Owen Smith"
  },
  "E14000825": {
    "consituency": "Morecambe and Lunesdale",
    "nomination_2015": "Andy Burnham",
    "nomination_2016": "Jeremy Corbyn"
  },
  "E14000826": {
    "consituency": "Morley and Outwood",
    "nomination_2015": "Yvette Cooper",
    "nomination_2016": "Owen Smith"
  },
  "S16000133": {
    "consituency": "Motherwell and Wishaw",
    "nomination_2015": "Jeremy Corbyn",
    "nomination_2016": ""
  },
  "S16000110": {
    "consituency": "Na h-Eileanan an Iar",
    "nomination_2015": "",
    "nomination_2016": ""
  },
  "W07000069": {
    "consituency": "Neath",
    "nomination_2015": "",
    "nomination_2016": ""
  },
  "E14000827": {
    "consituency": "New Forest East",
    "nomination_2015": "",
    "nomination_2016": "Jeremy Corbyn"
  },
  "E14000828": {
    "consituency": "New Forest West",
    "nomination_2015": "Andy Burnham",
    "nomination_2016": ""
  },
  "E14000829": {
    "consituency": "Newark",
    "nomination_2015": "",
    "nomination_2016": "Jeremy Corbyn"
  },
  "E14000830": {
    "consituency": "Newbury",
    "nomination_2015": "",
    "nomination_2016": ""
  },
  "E14000831": {
    "consituency": "Newcastle upon Tyne Central",
    "nomination_2015": "Jeremy Corbyn",
    "nomination_2016": "Jeremy Corbyn"
  },
  "E14000832": {
    "consituency": "Newcastle upon Tyne East",
    "nomination_2015": "Yvette Cooper",
    "nomination_2016": ""
  },
  "E14000833": {
    "consituency": "Newcastle upon Tyne North",
    "nomination_2015": "",
    "nomination_2016": "Owen Smith"
  },
  "E14000834": {
    "consituency": "Newcastle-under-Lyme",
    "nomination_2015": "Andy Burnham",
    "nomination_2016": "Jeremy Corbyn"
  },
  "W07000055": {
    "consituency": "Newport East",
    "nomination_2015": "Jeremy Corbyn",
    "nomination_2016": ""
  },
  "W07000056": {
    "consituency": "Newport West",
    "nomination_2015": "",
    "nomination_2016": ""
  },
  "E14000835": {
    "consituency": "Newton Abbot",
    "nomination_2015": "Liz Kendall",
    "nomination_2016": "Jeremy Corbyn"
  },
  "E14000836": {
    "consituency": "Normanton, Pontefract and Castleford",
    "nomination_2015": "Yvette Cooper",
    "nomination_2016": ""
  },
  "E14000837": {
    "consituency": "North Cornwall",
    "nomination_2015": "Jeremy Corbyn",
    "nomination_2016": ""
  },
  "E14000838": {
    "consituency": "North Devon",
    "nomination_2015": "Jeremy Corbyn",
    "nomination_2016": ""
  },
  "E14000839": {
    "consituency": "North Dorset",
    "nomination_2015": "",
    "nomination_2016": ""
  },
  "E14000840": {
    "consituency": "North Durham",
    "nomination_2015": "",
    "nomination_2016": ""
  },
  "E14000841": {
    "consituency": "North East Bedfordshire",
    "nomination_2015": "",
    "nomination_2016": ""
  },
  "E14000842": {
    "consituency": "North East Cambridgeshire",
    "nomination_2015": "",
    "nomination_2016": ""
  },
  "E14000843": {
    "consituency": "North East Derbyshire",
    "nomination_2015": "",
    "nomination_2016": ""
  },
  "S16000134": {
    "consituency": "North East Fife",
    "nomination_2015": "Yvette Cooper",
    "nomination_2016": ""
  },
  "E14000844": {
    "consituency": "North East Hampshire",
    "nomination_2015": "",
    "nomination_2016": ""
  },
  "E14000845": {
    "consituency": "North East Hertfordshire",
    "nomination_2015": "",
    "nomination_2016": ""
  },
  "E14000846": {
    "consituency": "North East Somerset",
    "nomination_2015": "",
    "nomination_2016": ""
  },
  "E14000847": {
    "consituency": "North Herefordshire",
    "nomination_2015": "Jeremy Corbyn",
    "nomination_2016": ""
  },
  "E14000848": {
    "consituency": "North Norfolk",
    "nomination_2015": "Jeremy Corbyn",
    "nomination_2016": "Jeremy Corbyn"
  },
  "E14000849": {
    "consituency": "North Shropshire",
    "nomination_2015": "Jeremy Corbyn",
    "nomination_2016": ""
  },
  "E14000850": {
    "consituency": "North Somerset",
    "nomination_2015": "Jeremy Corbyn",
    "nomination_2016": "Jeremy Corbyn"
  },
  "E14000851": {
    "consituency": "North Swindon",
    "nomination_2015": "Andy Burnham",
    "nomination_2016": ""
  },
  "E14000852": {
    "consituency": "North Thanet",
    "nomination_2015": "",
    "nomination_2016": ""
  },
  "E14000853": {
    "consituency": "North Tyneside",
    "nomination_2015": "Andy Burnham",
    "nomination_2016": ""
  },
  "E14000854": {
    "consituency": "North Warwickshire",
    "nomination_2015": "",
    "nomination_2016": ""
  },
  "E14000855": {
    "consituency": "North West Cambridgeshire",
    "nomination_2015": "",
    "nomination_2016": ""
  },
  "E14000856": {
    "consituency": "North West Durham",
    "nomination_2015": "",
    "nomination_2016": ""
  },
  "E14000857": {
    "consituency": "North West Hampshire",
    "nomination_2015": "Jeremy Corbyn",
    "nomination_2016": ""
  },
  "E14000858": {
    "consituency": "North West Leicestershire",
    "nomination_2015": "Andy Burnham",
    "nomination_2016": ""
  },
  "E14000859": {
    "consituency": "North West Norfolk",
    "nomination_2015": "",
    "nomination_2016": ""
  },
  "E14000860": {
    "consituency": "North Wiltshire",
    "nomination_2015": "",
    "nomination_2016": ""
  },
  "E14000861": {
    "consituency": "Northampton North",
    "nomination_2015": "Yvette Cooper",
    "nomination_2016": ""
  },
  "E14000862": {
    "consituency": "Northampton South",
    "nomination_2015": "Yvette Cooper",
    "nomination_2016": ""
  },
  "E14000863": {
    "consituency": "Norwich North",
    "nomination_2015": "Jeremy Corbyn",
    "nomination_2016": ""
  },
  "E14000864": {
    "consituency": "Norwich South",
    "nomination_2015": "Yvette Cooper",
    "nomination_2016": ""
  },
  "E14000865": {
    "consituency": "Nottingham East",
    "nomination_2015": "Jeremy Corbyn",
    "nomination_2016": ""
  },
  "E14000866": {
    "consituency": "Nottingham North",
    "nomination_2015": "",
    "nomination_2016": ""
  },
  "E14000867": {
    "consituency": "Nottingham South",
    "nomination_2015": "Jeremy Corbyn",
    "nomination_2016": "Owen Smith"
  },
  "E14000868": {
    "consituency": "Nuneaton",
    "nomination_2015": "",
    "nomination_2016": ""
  },
  "W07000074": {
    "consituency": "Ogmore",
    "nomination_2015": "Yvette Cooper",
    "nomination_2016": ""
  },
  "E14000869": {
    "consituency": "Old Bexley and Sidcup",
    "nomination_2015": "Yvette Cooper",
    "nomination_2016": "Jeremy Corbyn"
  },
  "E14000870": {
    "consituency": "Oldham East and Saddleworth",
    "nomination_2015": "Jeremy Corbyn",
    "nomination_2016": ""
  },
  "E14000871": {
    "consituency": "Oldham West and Royton",
    "nomination_2015": "Andy Burnham",
    "nomination_2016": ""
  },
  "S16000135": {
    "consituency": "Orkney Islands",
    "nomination_2015": "",
    "nomination_2016": ""
  },
  "E14000872": {
    "consituency": "Orpington",
    "nomination_2015": "",
    "nomination_2016": ""
  },
  "E14000873": {
    "consituency": "Oxford East",
    "nomination_2015": "",
    "nomination_2016": ""
  },
  "E14000874": {
    "consituency": "Oxford West and Abingdon",
    "nomination_2015": "",
    "nomination_2016": ""
  },
  "S16000136": {
    "consituency": "Paisley",
    "nomination_2015": "Andy Burnham",
    "nomination_2016": ""
  },
  "E14000875": {
    "consituency": "Pendle",
    "nomination_2015": "Yvette Cooper",
    "nomination_2016": ""
  },
  "E14000876": {
    "consituency": "Penistone and Stocksbridge",
    "nomination_2015": "",
    "nomination_2016": ""
  },
  "E14000877": {
    "consituency": "Penrith and The Border",
    "nomination_2015": "",
    "nomination_2016": ""
  },
  "S16000137": {
    "consituency": "Perthshire North",
    "nomination_2015": "",
    "nomination_2016": ""
  },
  "S16000138": {
    "consituency": "Perthshire South and Kinross-shire",
    "nomination_2015": "Jeremy Corbyn",
    "nomination_2016": ""
  },
  "E14000878": {
    "consituency": "Peterborough",
    "nomination_2015": "Jeremy Corbyn",
    "nomination_2016": "Jeremy Corbyn"
  },
  "E14000879": {
    "consituency": "Plymouth Moor View",
    "nomination_2015": "",
    "nomination_2016": ""
  },
  "E14000880": {
    "consituency": "Plymouth Sutton and Devonport",
    "nomination_2015": "",
    "nomination_2016": ""
  },
  "W07000075": {
    "consituency": "Pontypridd",
    "nomination_2015": "Andy Burnham",
    "nomination_2016": ""
  },
  "E14000881": {
    "consituency": "Poole",
    "nomination_2015": "",
    "nomination_2016": "Jeremy Corbyn"
  },
  "E14000882": {
    "consituency": "Poplar and Limehouse",
    "nomination_2015": "Andy Burnham",
    "nomination_2016": "Jeremy Corbyn"
  },
  "E14000883": {
    "consituency": "Portsmouth North",
    "nomination_2015": "",
    "nomination_2016": ""
  },
  "E14000884": {
    "consituency": "Portsmouth South",
    "nomination_2015": "Yvette Cooper",
    "nomination_2016": ""
  },
  "W07000065": {
    "consituency": "Preseli Pembrokeshire",
    "nomination_2015": "Jeremy Corbyn",
    "nomination_2016": "Jeremy Corbyn"
  },
  "E14000885": {
    "consituency": "Preston",
    "nomination_2015": "Jeremy Corbyn",
    "nomination_2016": ""
  },
  "E14000886": {
    "consituency": "Pudsey",
    "nomination_2015": "Andy Burnham",
    "nomination_2016": "Jeremy Corbyn"
  },
  "E14000887": {
    "consituency": "Putney",
    "nomination_2015": "",
    "nomination_2016": ""
  },
  "E14000888": {
    "consituency": "Rayleigh and Wickford",
    "nomination_2015": "",
    "nomination_2016": ""
  },
  "E14000889": {
    "consituency": "Reading East",
    "nomination_2015": "",
    "nomination_2016": "Owen Smith"
  },
  "E14000890": {
    "consituency": "Reading West",
    "nomination_2015": "",
    "nomination_2016": "Jeremy Corbyn"
  },
  "E14000891": {
    "consituency": "Redcar",
    "nomination_2015": "",
    "nomination_2016": ""
  },
  "E14000892": {
    "consituency": "Redditch",
    "nomination_2015": "Andy Burnham",
    "nomination_2016": ""
  },
  "E14000893": {
    "consituency": "Reigate",
    "nomination_2015": "Yvette Cooper",
    "nomination_2016": "Jeremy Corbyn"
  },
  "S16000139": {
    "consituency": "Renfrewshire North and West",
    "nomination_2015": "",
    "nomination_2016": ""
  },
  "S16000140": {
    "consituency": "Renfrewshire South",
    "nomination_2015": "Yvette Cooper",
    "nomination_2016": ""
  },
  "W07000052": {
    "consituency": "Rhondda",
    "nomination_2015": "",
    "nomination_2016": ""
  },
  "E14000894": {
    "consituency": "Ribble Valley",
    "nomination_2015": "",
    "nomination_2016": ""
  },
  "E14000895": {
    "consituency": "Richmond (Yorks)",
    "nomination_2015": "",
    "nomination_2016": ""
  },
  "E14000896": {
    "consituency": "Richmond Park",
    "nomination_2015": "Jeremy Corbyn",
    "nomination_2016": "Owen Smith"
  },
  "E14000897": {
    "consituency": "Rochdale",
    "nomination_2015": "",
    "nomination_2016": ""
  },
  "E14000898": {
    "consituency": "Rochester and Strood",
    "nomination_2015": "Andy Burnham",
    "nomination_2016": "Jeremy Corbyn"
  },
  "E14000899": {
    "consituency": "Rochford and Southend East",
    "nomination_2015": "Yvette Cooper",
    "nomination_2016": ""
  },
  "E14000900": {
    "consituency": "Romford",
    "nomination_2015": "Andy Burnham",
    "nomination_2016": "Jeremy Corbyn"
  },
  "E14000901": {
    "consituency": "Romsey and Southampton North",
    "nomination_2015": "Yvette Cooper",
    "nomination_2016": ""
  },
  "E14000902": {
    "consituency": "Rossendale and Darwen",
    "nomination_2015": "",
    "nomination_2016": ""
  },
  "E14000903": {
    "consituency": "Rother Valley",
    "nomination_2015": "",
    "nomination_2016": ""
  },
  "E14000904": {
    "consituency": "Rotherham",
    "nomination_2015": "",
    "nomination_2016": ""
  },
  "E14000905": {
    "consituency": "Rugby",
    "nomination_2015": "Jeremy Corbyn",
    "nomination_2016": ""
  },
  "E14000906": {
    "consituency": "Ruislip, Northwood and Pinner",
    "nomination_2015": "Andy Burnham",
    "nomination_2016": ""
  },
  "E14000907": {
    "consituency": "Runnymede and Weybridge",
    "nomination_2015": "Yvette Cooper",
    "nomination_2016": "Owen Smith"
  },
  "E14000908": {
    "consituency": "Rushcliffe",
    "nomination_2015": "",
    "nomination_2016": ""
  },
  "S16000141": {
    "consituency": "Rutherglen",
    "nomination_2015": "Andy Burnham",
    "nomination_2016": ""
  },
  "E14000909": {
    "consituency": "Rutland and Melton",
    "nomination_2015": "Yvette Cooper",
    "nomination_2016": ""
  },
  "E14000910": {
    "consituency": "Saffron Walden",
    "nomination_2015": "Yvette Cooper",
    "nomination_2016": ""
  },
  "E14000911": {
    "consituency": "Salford and Eccles",
    "nomination_2015": "Jeremy Corbyn",
    "nomination_2016": "Jeremy Corbyn"
  },
  "E14000912": {
    "consituency": "Salisbury",
    "nomination_2015": "",
    "nomination_2016": "Jeremy Corbyn"
  },
  "E14000913": {
    "consituency": "Scarborough and Whitby",
    "nomination_2015": "Jeremy Corbyn",
    "nomination_2016": "Jeremy Corbyn"
  },
  "E14000914": {
    "consituency": "Scunthorpe",
    "nomination_2015": "Jeremy Corbyn",
    "nomination_2016": "Jeremy Corbyn"
  },
  "E14000915": {
    "consituency": "Sedgefield",
    "nomination_2015": "Liz Kendall",
    "nomination_2016": ""
  },
  "E14000916": {
    "consituency": "Sefton Central",
    "nomination_2015": "Andy Burnham",
    "nomination_2016": ""
  },
  "E14000917": {
    "consituency": "Selby and Ainsty",
    "nomination_2015": "Yvette Cooper",
    "nomination_2016": ""
  },
  "E14000918": {
    "consituency": "Sevenoaks",
    "nomination_2015": "",
    "nomination_2016": ""
  },
  "E14000919": {
    "consituency": "Sheffield Central",
    "nomination_2015": "",
    "nomination_2016": ""
  },
  "E14000920": {
    "consituency": "Sheffield South East",
    "nomination_2015": "Andy Burnham",
    "nomination_2016": ""
  },
  "E14000921": {
    "consituency": "Sheffield Brightside and Hillsborough",
    "nomination_2015": "Andy Burnham",
    "nomination_2016": ""
  },
  "E14000922": {
    "consituency": "Sheffield Hallam",
    "nomination_2015": "",
    "nomination_2016": ""
  },
  "E14000923": {
    "consituency": "Sheffield Heeley",
    "nomination_2015": "",
    "nomination_2016": ""
  },
  "E14000924": {
    "consituency": "Sherwood",
    "nomination_2015": "Jeremy Corbyn",
    "nomination_2016": ""
  },
  "S16000142": {
    "consituency": "Shetland Islands",
    "nomination_2015": "",
    "nomination_2016": ""
  },
  "E14000925": {
    "consituency": "Shipley",
    "nomination_2015": "Yvette Cooper",
    "nomination_2016": ""
  },
  "E14000926": {
    "consituency": "Shrewsbury and Atcham",
    "nomination_2015": "Jeremy Corbyn",
    "nomination_2016": ""
  },
  "E14000927": {
    "consituency": "Sittingbourne and Sheppey",
    "nomination_2015": "Yvette Cooper",
    "nomination_2016": ""
  },
  "E14000928": {
    "consituency": "Skipton and Ripon",
    "nomination_2015": "Jeremy Corbyn",
    "nomination_2016": ""
  },
  "S16000143": {
    "consituency": "Skye Lochaber and Badenoch",
    "nomination_2015": "",
    "nomination_2016": ""
  },
  "E14000929": {
    "consituency": "Sleaford and North Hykeham",
    "nomination_2015": "Yvette Cooper",
    "nomination_2016": ""
  },
  "E14000930": {
    "consituency": "Slough",
    "nomination_2015": "Andy Burnham",
    "nomination_2016": ""
  },
  "E14000931": {
    "consituency": "Solihull",
    "nomination_2015": "",
    "nomination_2016": ""
  },
  "E14000932": {
    "consituency": "Somerton and Frome",
    "nomination_2015": "Jeremy Corbyn",
    "nomination_2016": ""
  },
  "E14000933": {
    "consituency": "South Basildon and East Thurrock",
    "nomination_2015": "Jeremy Corbyn",
    "nomination_2016": ""
  },
  "E14000934": {
    "consituency": "South Cambridgeshire",
    "nomination_2015": "",
    "nomination_2016": "Jeremy Corbyn"
  },
  "E14000935": {
    "consituency": "South Derbyshire",
    "nomination_2015": "Jeremy Corbyn",
    "nomination_2016": ""
  },
  "E14000936": {
    "consituency": "South Dorset",
    "nomination_2015": "Yvette Cooper",
    "nomination_2016": "Jeremy Corbyn"
  },
  "E14000937": {
    "consituency": "South East Cambridgeshire",
    "nomination_2015": "",
    "nomination_2016": ""
  },
  "E14000938": {
    "consituency": "South East Cornwall",
    "nomination_2015": "Jeremy Corbyn",
    "nomination_2016": "Jeremy Corbyn"
  },
  "E14000939": {
    "consituency": "South Holland and The Deepings",
    "nomination_2015": "",
    "nomination_2016": ""
  },
  "E14000940": {
    "consituency": "South Leicestershire",
    "nomination_2015": "Andy Burnham",
    "nomination_2016": ""
  },
  "E14000941": {
    "consituency": "South Norfolk",
    "nomination_2015": "",
    "nomination_2016": ""
  },
  "E14000942": {
    "consituency": "South Northamptonshire",
    "nomination_2015": "Jeremy Corbyn",
    "nomination_2016": ""
  },
  "E14000943": {
    "consituency": "South Ribble",
    "nomination_2015": "Jeremy Corbyn",
    "nomination_2016": ""
  },
  "E14000944": {
    "consituency": "South Shields",
    "nomination_2015": "Andy Burnham",
    "nomination_2016": ""
  },
  "E14000945": {
    "consituency": "South Staffordshire",
    "nomination_2015": "",
    "nomination_2016": ""
  },
  "E14000946": {
    "consituency": "South Suffolk",
    "nomination_2015": "Jeremy Corbyn",
    "nomination_2016": ""
  },
  "E14000947": {
    "consituency": "South Swindon",
    "nomination_2015": "",
    "nomination_2016": "Owen Smith"
  },
  "E14000948": {
    "consituency": "South Thanet",
    "nomination_2015": "",
    "nomination_2016": "Jeremy Corbyn"
  },
  "E14000949": {
    "consituency": "South West Bedfordshire",
    "nomination_2015": "",
    "nomination_2016": "Jeremy Corbyn"
  },
  "E14000950": {
    "consituency": "South West Devon",
    "nomination_2015": "Andy Burnham",
    "nomination_2016": "Jeremy Corbyn"
  },
  "E14000951": {
    "consituency": "South West Hertfordshire",
    "nomination_2015": "",
    "nomination_2016": ""
  },
  "E14000952": {
    "consituency": "South West Norfolk",
    "nomination_2015": "Yvette Cooper",
    "nomination_2016": "Jeremy Corbyn"
  },
  "E14000953": {
    "consituency": "South West Surrey",
    "nomination_2015": "Yvette Cooper",
    "nomination_2016": ""
  },
  "E14000954": {
    "consituency": "South West Wiltshire",
    "nomination_2015": "Jeremy Corbyn",
    "nomination_2016": ""
  },
  "E14000955": {
    "consituency": "Southampton Itchen",
    "nomination_2015": "Jeremy Corbyn",
    "nomination_2016": "Jeremy Corbyn"
  },
  "E14000956": {
    "consituency": "Southampton Test",
    "nomination_2015": "Jeremy Corbyn",
    "nomination_2016": "Jeremy Corbyn"
  },
  "E14000957": {
    "consituency": "Southend West",
    "nomination_2015": "Yvette Cooper",
    "nomination_2016": ""
  },
  "E14000958": {
    "consituency": "Southport",
    "nomination_2015": "Andy Burnham",
    "nomination_2016": ""
  },
  "E14000959": {
    "consituency": "Spelthorne",
    "nomination_2015": "",
    "nomination_2016": ""
  },
  "E14000960": {
    "consituency": "St Albans",
    "nomination_2015": "Yvette Cooper",
    "nomination_2016": ""
  },
  "E14000961": {
    "consituency": "St Austell and Newquay",
    "nomination_2015": "Jeremy Corbyn",
    "nomination_2016": ""
  },
  "E14000962": {
    "consituency": "St Helens North",
    "nomination_2015": "Andy Burnham",
    "nomination_2016": ""
  },
  "E14000963": {
    "consituency": "St Helens South and Whiston",
    "nomination_2015": "Yvette Cooper",
    "nomination_2016": "Jeremy Corbyn"
  },
  "E14000964": {
    "consituency": "St Ives",
    "nomination_2015": "Jeremy Corbyn",
    "nomination_2016": ""
  },
  "E14000965": {
    "consituency": "Stafford",
    "nomination_2015": "",
    "nomination_2016": ""
  },
  "E14000966": {
    "consituency": "Staffordshire Moorlands",
    "nomination_2015": "",
    "nomination_2016": ""
  },
  "E14000967": {
    "consituency": "Stalybridge and Hyde",
    "nomination_2015": "Jeremy Corbyn",
    "nomination_2016": ""
  },
  "E14000968": {
    "consituency": "Stevenage",
    "nomination_2015": "Yvette Cooper",
    "nomination_2016": ""
  },
  "S16000144": {
    "consituency": "Stirling",
    "nomination_2015": "",
    "nomination_2016": ""
  },
  "E14000969": {
    "consituency": "Stockport",
    "nomination_2015": "",
    "nomination_2016": ""
  },
  "E14000970": {
    "consituency": "Stockton North",
    "nomination_2015": "Andy Burnham",
    "nomination_2016": ""
  },
  "E14000971": {
    "consituency": "Stockton South",
    "nomination_2015": "",
    "nomination_2016": ""
  },
  "E14000972": {
    "consituency": "Stoke-on-Trent Central",
    "nomination_2015": "Yvette Cooper",
    "nomination_2016": ""
  },
  "E14000973": {
    "consituency": "Stoke-on-Trent North",
    "nomination_2015": "",
    "nomination_2016": ""
  },
  "E14000974": {
    "consituency": "Stoke-on-Trent South",
    "nomination_2015": "Andy Burnham",
    "nomination_2016": "Jeremy Corbyn"
  },
  "E14000975": {
    "consituency": "Stone",
    "nomination_2015": "",
    "nomination_2016": ""
  },
  "E14000976": {
    "consituency": "Stourbridge",
    "nomination_2015": "",
    "nomination_2016": ""
  },
  "E14000977": {
    "consituency": "Stratford-on-Avon",
    "nomination_2015": "Jeremy Corbyn",
    "nomination_2016": ""
  },
  "S16000145": {
    "consituency": "Strathkelvin and Bearsden",
    "nomination_2015": "Andy Burnham",
    "nomination_2016": ""
  },
  "E14000978": {
    "consituency": "Streatham",
    "nomination_2015": "Liz Kendall",
    "nomination_2016": "Owen Smith"
  },
  "E14000979": {
    "consituency": "Stretford and Urmston",
    "nomination_2015": "",
    "nomination_2016": "Jeremy Corbyn"
  },
  "E14000980": {
    "consituency": "Stroud",
    "nomination_2015": "",
    "nomination_2016": ""
  },
  "E14000981": {
    "consituency": "Suffolk Coastal",
    "nomination_2015": "",
    "nomination_2016": ""
  },
  "E14000982": {
    "consituency": "Sunderland Central",
    "nomination_2015": "Jeremy Corbyn",
    "nomination_2016": ""
  },
  "E14000983": {
    "consituency": "Surrey Heath",
    "nomination_2015": "Yvette Cooper",
    "nomination_2016": ""
  },
  "E14000984": {
    "consituency": "Sutton and Cheam",
    "nomination_2015": "Jeremy Corbyn",
    "nomination_2016": "Jeremy Corbyn"
  },
  "E14000985": {
    "consituency": "Sutton Coldfield",
    "nomination_2015": "",
    "nomination_2016": "Jeremy Corbyn"
  },
  "W07000048": {
    "consituency": "Swansea East",
    "nomination_2015": "Jeremy Corbyn",
    "nomination_2016": ""
  },
  "W07000047": {
    "consituency": "Swansea West",
    "nomination_2015": "Jeremy Corbyn",
    "nomination_2016": "Jeremy Corbyn"
  },
  "E14000986": {
    "consituency": "Tamworth",
    "nomination_2015": "",
    "nomination_2016": ""
  },
  "E14000987": {
    "consituency": "Tatton",
    "nomination_2015": "",
    "nomination_2016": ""
  },
  "E14000988": {
    "consituency": "Taunton Deane",
    "nomination_2015": "",
    "nomination_2016": ""
  },
  "E14000989": {
    "consituency": "Telford",
    "nomination_2015": "Andy Burnham",
    "nomination_2016": ""
  },
  "E14000990": {
    "consituency": "Tewkesbury",
    "nomination_2015": "Yvette Cooper",
    "nomination_2016": "Jeremy Corbyn"
  },
  "E14000991": {
    "consituency": "The Cotswolds",
    "nomination_2015": "",
    "nomination_2016": "Jeremy Corbyn"
  },
  "E14000992": {
    "consituency": "The Wrekin",
    "nomination_2015": "",
    "nomination_2016": ""
  },
  "E14000993": {
    "consituency": "Thirsk and Malton",
    "nomination_2015": "Jeremy Corbyn",
    "nomination_2016": ""
  },
  "E14000994": {
    "consituency": "Thornbury and Yate",
    "nomination_2015": "Jeremy Corbyn",
    "nomination_2016": ""
  },
  "E14000995": {
    "consituency": "Thurrock",
    "nomination_2015": "Yvette Cooper",
    "nomination_2016": "Jeremy Corbyn"
  },
  "E14000996": {
    "consituency": "Tiverton and Honiton",
    "nomination_2015": "Yvette Cooper",
    "nomination_2016": ""
  },
  "E14000997": {
    "consituency": "Tonbridge and Malling",
    "nomination_2015": "",
    "nomination_2016": ""
  },
  "E14000998": {
    "consituency": "Tooting",
    "nomination_2015": "Yvette Cooper",
    "nomination_2016": ""
  },
  "E14000999": {
    "consituency": "Torbay",
    "nomination_2015": "",
    "nomination_2016": ""
  },
  "W07000053": {
    "consituency": "Torfaen",
    "nomination_2015": "Andy Burnham",
    "nomination_2016": ""
  },
  "E14001000": {
    "consituency": "Torridge and West Devon",
    "nomination_2015": "",
    "nomination_2016": ""
  },
  "E14001001": {
    "consituency": "Totnes",
    "nomination_2015": "Yvette Cooper",
    "nomination_2016": "Jeremy Corbyn"
  },
  "E14001002": {
    "consituency": "Tottenham",
    "nomination_2015": "Jeremy Corbyn",
    "nomination_2016": ""
  },
  "E14001003": {
    "consituency": "Truro and Falmouth",
    "nomination_2015": "Yvette Cooper",
    "nomination_2016": "Jeremy Corbyn"
  },
  "E14001004": {
    "consituency": "Tunbridge Wells",
    "nomination_2015": "Andy Burnham",
    "nomination_2016": ""
  },
  "E14001005": {
    "consituency": "Twickenham",
    "nomination_2015": "Yvette Cooper",
    "nomination_2016": ""
  },
  "E14001006": {
    "consituency": "Tynemouth",
    "nomination_2015": "",
    "nomination_2016": ""
  },
  "S16000146": {
    "consituency": "Uddingston and Bellshill",
    "nomination_2015": "Andy Burnham",
    "nomination_2016": ""
  },
  "E14001007": {
    "consituency": "Uxbridge and South Ruislip",
    "nomination_2015": "Jeremy Corbyn",
    "nomination_2016": ""
  },
  "W07000060": {
    "consituency": "Vale of Clwyd",
    "nomination_2015": "",
    "nomination_2016": ""
  },
  "W07000078": {
    "consituency": "Vale of Glamorgan",
    "nomination_2015": "Yvette Cooper",
    "nomination_2016": ""
  },
  "E14001008": {
    "consituency": "Vauxhall",
    "nomination_2015": "Liz Kendall",
    "nomination_2016": "Owen Smith"
  },
  "E14001009": {
    "consituency": "Wakefield",
    "nomination_2015": "Jeremy Corbyn",
    "nomination_2016": "Jeremy Corbyn"
  },
  "E14001010": {
    "consituency": "Wallasey",
    "nomination_2015": "Jeremy Corbyn",
    "nomination_2016": ""
  },
  "E14001011": {
    "consituency": "Walsall North",
    "nomination_2015": "",
    "nomination_2016": ""
  },
  "E14001012": {
    "consituency": "Walsall South",
    "nomination_2015": "",
    "nomination_2016": ""
  },
  "E14001013": {
    "consituency": "Walthamstow",
    "nomination_2015": "Jeremy Corbyn",
    "nomination_2016": ""
  },
  "E14001014": {
    "consituency": "Wansbeck",
    "nomination_2015": "Andy Burnham",
    "nomination_2016": ""
  },
  "E14001015": {
    "consituency": "Wantage",
    "nomination_2015": "",
    "nomination_2016": ""
  },
  "E14001016": {
    "consituency": "Warley",
    "nomination_2015": "Yvette Cooper",
    "nomination_2016": ""
  },
  "E14001017": {
    "consituency": "Warrington North",
    "nomination_2015": "Andy Burnham",
    "nomination_2016": ""
  },
  "E14001018": {
    "consituency": "Warrington South",
    "nomination_2015": "Yvette Cooper",
    "nomination_2016": "Owen Smith"
  },
  "E14001019": {
    "consituency": "Warwick and Leamington",
    "nomination_2015": "Jeremy Corbyn",
    "nomination_2016": ""
  },
  "E14001020": {
    "consituency": "Washington and Sunderland West",
    "nomination_2015": "Jeremy Corbyn",
    "nomination_2016": ""
  },
  "E14001021": {
    "consituency": "Watford",
    "nomination_2015": "Yvette Cooper",
    "nomination_2016": ""
  },
  "E14001022": {
    "consituency": "Waveney",
    "nomination_2015": "",
    "nomination_2016": ""
  },
  "E14001023": {
    "consituency": "Wealden",
    "nomination_2015": "Jeremy Corbyn",
    "nomination_2016": ""
  },
  "E14001024": {
    "consituency": "Weaver Vale",
    "nomination_2015": "",
    "nomination_2016": ""
  },
  "E14001025": {
    "consituency": "Wellingborough",
    "nomination_2015": "",
    "nomination_2016": ""
  },
  "E14001026": {
    "consituency": "Wells",
    "nomination_2015": "",
    "nomination_2016": ""
  },
  "E14001027": {
    "consituency": "Welwyn Hatfield",
    "nomination_2015": "",
    "nomination_2016": ""
  },
  "E14001028": {
    "consituency": "Wentworth and Dearne",
    "nomination_2015": "",
    "nomination_2016": ""
  },
  "E14001029": {
    "consituency": "West Bromwich East",
    "nomination_2015": "",
    "nomination_2016": ""
  },
  "E14001030": {
    "consituency": "West Bromwich West",
    "nomination_2015": "",
    "nomination_2016": ""
  },
  "E14001031": {
    "consituency": "West Dorset",
    "nomination_2015": "",
    "nomination_2016": ""
  },
  "E14001032": {
    "consituency": "West Ham",
    "nomination_2015": "Jeremy Corbyn",
    "nomination_2016": "Owen Smith"
  },
  "E14001033": {
    "consituency": "West Lancashire",
    "nomination_2015": "Andy Burnham",
    "nomination_2016": ""
  },
  "E14001034": {
    "consituency": "West Suffolk",
    "nomination_2015": "Jeremy Corbyn",
    "nomination_2016": "Jeremy Corbyn"
  },
  "E14001035": {
    "consituency": "West Worcestershire",
    "nomination_2015": "",
    "nomination_2016": ""
  },
  "E14001036": {
    "consituency": "Westminster North",
    "nomination_2015": "Yvette Cooper",
    "nomination_2016": "Owen Smith"
  },
  "E14001037": {
    "consituency": "Westmorland and Lonsdale",
    "nomination_2015": "Jeremy Corbyn",
    "nomination_2016": "Jeremy Corbyn"
  },
  "E14001038": {
    "consituency": "Weston-Super-Mare",
    "nomination_2015": "",
    "nomination_2016": ""
  },
  "E14001039": {
    "consituency": "Wigan",
    "nomination_2015": "",
    "nomination_2016": ""
  },
  "E14001040": {
    "consituency": "Wimbledon",
    "nomination_2015": "Yvette Cooper",
    "nomination_2016": "Owen Smith"
  },
  "E14001041": {
    "consituency": "Winchester",
    "nomination_2015": "",
    "nomination_2016": ""
  },
  "E14001042": {
    "consituency": "Windsor",
    "nomination_2015": "",
    "nomination_2016": ""
  },
  "E14001043": {
    "consituency": "Wirral South",
    "nomination_2015": "Andy Burnham",
    "nomination_2016": "Jeremy Corbyn"
  },
  "E14001044": {
    "consituency": "Wirral West",
    "nomination_2015": "Yvette Cooper",
    "nomination_2016": ""
  },
  "E14001045": {
    "consituency": "Witham",
    "nomination_2015": "",
    "nomination_2016": ""
  },
  "E14001046": {
    "consituency": "Witney",
    "nomination_2015": "Yvette Cooper",
    "nomination_2016": ""
  },
  "E14001047": {
    "consituency": "Woking",
    "nomination_2015": "Andy Burnham",
    "nomination_2016": ""
  },
  "E14001048": {
    "consituency": "Wokingham",
    "nomination_2015": "",
    "nomination_2016": "Jeremy Corbyn"
  },
  "E14001049": {
    "consituency": "Wolverhampton North East",
    "nomination_2015": "Andy Burnham",
    "nomination_2016": ""
  },
  "E14001050": {
    "consituency": "Wolverhampton South East",
    "nomination_2015": "Liz Kendall",
    "nomination_2016": ""
  },
  "E14001051": {
    "consituency": "Wolverhampton South West",
    "nomination_2015": "Jeremy Corbyn",
    "nomination_2016": ""
  },
  "E14001052": {
    "consituency": "Worcester",
    "nomination_2015": "",
    "nomination_2016": ""
  },
  "E14001053": {
    "consituency": "Workington",
    "nomination_2015": "Andy Burnham",
    "nomination_2016": ""
  },
  "E14001054": {
    "consituency": "Worsley and Eccles South",
    "nomination_2015": "Andy Burnham",
    "nomination_2016": ""
  },
  "E14001055": {
    "consituency": "Worthing West",
    "nomination_2015": "",
    "nomination_2016": "Jeremy Corbyn"
  },
  "W07000044": {
    "consituency": "Wrexham",
    "nomination_2015": "Andy Burnham",
    "nomination_2016": ""
  },
  "E14001056": {
    "consituency": "Wycombe",
    "nomination_2015": "Jeremy Corbyn",
    "nomination_2016": ""
  },
  "E14001057": {
    "consituency": "Wyre and Preston North",
    "nomination_2015": "",
    "nomination_2016": ""
  },
  "E14001058": {
    "consituency": "Wyre Forest",
    "nomination_2015": "Andy Burnham",
    "nomination_2016": ""
  },
  "E14001059": {
    "consituency": "Wythenshawe and Sale East",
    "nomination_2015": "Jeremy Corbyn",
    "nomination_2016": ""
  },
  "E14001060": {
    "consituency": "Yeovil",
    "nomination_2015": "Yvette Cooper",
    "nomination_2016": ""
  },
  "W07000041": {
    "consituency": "Ynys Mn",
    "nomination_2015": "Jeremy Corbyn",
    "nomination_2016": "Jeremy Corbyn"
  },
  "E14001061": {
    "consituency": "York Central",
    "nomination_2015": "",
    "nomination_2016": ""
  },
  "E14001062": {
    "consituency": "York Outer",
    "nomination_2015": "",
    "nomination_2016": ""
  },
  "NorthernIreland": {
    "consituency": "Northern Ireland",
    "nomination_2015": "Andy Burnham",
    "nomination_2016": ""
  }
}
